bazarrbulksync-0.1.0.dist-info/licenses/LICENSE
cli/__init__.py
cli/cli.py
cli/config.py
sync/__init__.py
sync/bazarr.py
sync/sync.py
tests/__init__.py
tests/config.py
tests/test_bazarr.py
tests/test_bazarr_api.py
bazarrbulksync-0.1.0.dist-info/METADATA
bazarrbulksync-0.1.0.dist-info/WHEEL
bazarrbulksync-0.1.0.dist-info/entry_points.txt
bazarrbulksync-0.1.0.dist-info/top_level.txt
bazarrbulksync-0.1.0.dist-info/RECORD
