Metadata-Version: 2.4
Name: bazarrbulksync
Version: 0.1.0
Summary: An optimized command-line tool for bulk syncing media subtitles in Bazarr
Home-page: https://github.com/BrianWeiHaoMa/bazarrbulksync
Author: Brian Wei Hao Ma
Author-email: brianmaytc@gmail.com
License: MIT
Keywords: bazarr,subtitles,subtitle-sync,subtitle-synchronization,media,video,movies,tv,cli,command-line,automation,bulk,sync,media-server,plex,emby,jellyfin,sonarr,radarr,streaming
Classifier: Development Status :: 4 - Beta
Classifier: License :: OSI Approved :: MIT License
Classifier: Operating System :: OS Independent
Classifier: Topic :: Utilities
Classifier: Topic :: Multimedia :: Video
Classifier: Intended Audience :: System Administrators
Classifier: Intended Audience :: End Users/Desktop
Classifier: Intended Audience :: Information Technology
Classifier: Programming Language :: Python :: 3.10
Classifier: Programming Language :: Python :: 3.11
Classifier: Programming Language :: Python :: 3.12
Classifier: Programming Language :: Python :: 3.13
Classifier: Programming Language :: Python :: 3 :: Only
Requires-Python: >=3.10
License-File: LICENSE
Requires-Dist: PyYAML<7.0.0,>=6.0.0
Requires-Dist: requests<3.0.0,>=2.32.0
Dynamic: author
Dynamic: author-email
Dynamic: classifier
Dynamic: description
Dynamic: description-content-type
Dynamic: home-page
Dynamic: keywords
Dynamic: license
Dynamic: license-file
Dynamic: requires-dist
Dynamic: requires-python
Dynamic: summary
